data.py
lungdamagedetectioncli-1.0.0.dist-info/METADATA
lungdamagedetectioncli-1.0.0.dist-info/WHEEL
lungdamagedetectioncli-1.0.0.dist-info/entry_points.txt
lungdamagedetectioncli-1.0.0.dist-info/licenses/LICENSE
main.py
model.py
settings.py
tester.py
trainer.py
lungdamagedetectioncli-1.0.0.dist-info/RECORD
