Metadata-Version: 2.1
Name: LungDamageDetectionCLI
Version: 1.0.0
Summary: CLI application for training and inferring lung injury detection model
Keywords: detection,lung injuries,dicom,unet,pytorch,torch,cli,computer vision,medicine,covid-19
Author-Email: grottI0 <chernega.bk@gmail.com>
License: MIT License
Classifier: Development Status :: 5 - Production/Stable
Classifier: Programming Language :: Python :: 3
Classifier: Topic :: Scientific/Engineering :: Medical Science Apps.
Classifier: Intended Audience :: Healthcare Industry
Classifier: License :: OSI Approved :: MIT License
Project-URL: Homepage, https://github.com/mtuciru/Lung-Damage-Detection-CLI
Project-URL: Repository, https://github.com/mtuciru/Lung-Damage-Detection-CLI.git
Requires-Python: ==3.10.*
Requires-Dist: torch==2.2.0
Requires-Dist: pydicom==2.4.4
Requires-Dist: torchvision==0.17.0
Requires-Dist: numpy<2.0.0
Requires-Dist: tqdm==4.66.2
Requires-Dist: scikit-learn==1.4.1.post1
Requires-Dist: pydantic-settings>=2.3.4
